{
  "1": {
    "time": "09:00",
    "description": "「慈聖宮」前的一排老店是城裡最真心不騙的小吃攤，坐在榕樹下吃碗肉粥或豬腳麵線，享用老台北的愜意中式早餐。"
  },
  "2": {
    "time": "10:00",
    "description": "吃完散步去百年老店「林華泰茶行」或「林茂森茶行」買些好茶當伴手禮。"
  },
  "3": {
    "time": "11:00",
    "description": "由迪化街北端逛起：老字號有糕餅名店「李亭香」、烏魚子老店「李日勝」與竹器行「林豐益商行」；新進駐的店家則有販售安心食材的「大稻埕259」、選品店「你好我好」、生活風格品牌「蘑菇」與創作者基地「URS155」。"
  },
  "4": {
    "time": "12:30",
    "description": "在「聯藝程」裡以台灣食材入味的歐亞料理「孔雀」用餐，或走到永樂市場附近享用各式小吃，私心推薦「永樂米苔目」與民樂街上的「紅燒土托魚羹」。"
  },
  "5": {
    "time": "14:00",
    "description": "不管單身與否，都來「霞海城隍廟」跟月老祈求感情順利吧！接著穿梭各式小店、茶館、咖啡館進駐的「民藝埕」、「眾藝埕」與「小藝埕」，再去「印花樂」採買印花布紀念品。"
  },
  "6": {
    "time": "16:00",
    "description": "喜愛獨立刊物的你請直接搭車前往「下北沢世代」，更愛老街風情的朋友這裡還有許多老建築和小店值得探險。"
  },
  "7": {
    "time": "17:30",
    "description": "沒事來「龍山寺」拜拜保平安，有事可跟觀音菩薩求籤解惑。"
  },
  "8": {
    "time": "18:30",
    "description": " 晚餐就在艋舺老街吃傳統小吃，「蘇家肉圓油粿」、「兩喜號魷魚羹」等任君挑選，吃完「龍都冰果室」來碗水果冰。"
  },
  "9": {
    "time": "19:30",
    "description": "散步到貴陽街，吃一球古早味的「永富冰淇淋」，繼續前往西本願寺廣場，在「八拾捌茶」喝杯暖心的台灣花茶。"
  },
  "10": {
    "time": "20:30",
    "description": "日治時期曾是庶民市場的古蹟「西門紅樓」，如今成為文創基地，一樓商場有許多新興品牌進駐；紅樓後方是著名的同志露天酒吧區，氣氛輕鬆愉快，不妨坐下開瓶啤酒。"
  },
  "11": {
    "time": "22:00",
    "description": "來由製冰工廠改造、挑高寬敞的「Woolloomooloo」喝杯調酒放鬆身心，細細回味今日的新舊台北之旅。 "
  }
}
